dummy_dbutils/__init__.py
dummy_dbutils/dbutils_class.py
dummy_dbutils-0.0.10.dist-info/METADATA
dummy_dbutils-0.0.10.dist-info/WHEEL
dummy_dbutils-0.0.10.dist-info/top_level.txt
dummy_dbutils-0.0.10.dist-info/RECORD
