Metadata-Version: 2.1
Name: dummy_dbutils
Version: 0.0.10
Summary: Dummy Scripts for Databricks dbutils
Classifier: Development Status :: 1 - Planning
Classifier: Intended Audience :: Developers
Classifier: Programming Language :: Python :: 3
Classifier: Operating System :: Unix
Classifier: Operating System :: MacOS :: MacOS X
Classifier: Operating System :: Microsoft :: Windows
